{
  "cities": [
    {
      "id": "8217",
      "cityName": "La Puebla de Valverde",
      "country": "Spain",
      "emoji": "https://flagcdn.com/es.svg",
      "date": "2025-04-15T08:48:24.690Z",
      "notes": "",
      "position": {
        "lat": "40.317231732315236",
        "lng": "-0.9613037109375001"
      }
    },
    {
      "id": "85dc",
      "cityName": "Idri",
      "country": "Libya",
      "emoji": "https://flagcdn.com/ly.svg",
      "date": "2025-04-15T08:48:48.086Z",
      "notes": "",
      "position": {
        "lat": "28.38173504322311",
        "lng": "10.079956054687502"
      }
    },
    {
      "id": "3b18",
      "cityName": "Bardai",
      "country": "Chad",
      "emoji": "https://flagcdn.com/td.svg",
      "date": "2025-04-15T08:49:00.864Z",
      "notes": "",
      "position": {
        "lat": "20.52993312517078",
        "lng": "18.583374023437504"
      }
    }
  ]
}